{"py/object": "rasa.core.featurizers.tracker_featurizers.MaxHistoryTrackerFeaturizer", "state_featurizer": {"py/object": "rasa.core.featurizers.single_state_featurizer.SingleStateFeaturizer", "_default_feature_states": {"intent": {"affirm": 0, "back": 1, "bot_challenge": 2, "deny": 3, "give_feedback": 4, "give_rating": 5, "goodbye": 6, "greet": 7, "mood_great": 8, "mood_unhappy": 9, "nlu_fallback": 10, "out_of_scope": 11, "restart": 12, "select_faq_category": 13, "select_main_option": 14, "session_start": 15}, "action_name": {"action_listen": 0, "action_restart": 1, "action_session_start": 2, "action_default_fallback": 3, "action_deactivate_loop": 4, "action_revert_fallback_events": 5, "action_default_ask_affirmation": 6, "action_default_ask_rephrase": 7, "action_two_stage_fallback": 8, "action_unlikely_intent": 9, "action_back": 10, "...": 11, "action_extract_slots": 12, "utter_greet": 13, "action_show_main_menu": 14, "utter_greet_with_name": 15, "action_handle_option": 16, "action_handle_affirm": 17, "action_handle_rating": 18, "action_handle_feedback": 19, "submit_feedback_form": 20, "submit_customer_info_form": 21, "action_ask_name": 22, "action_save_name": 23, "action_deactivate_form": 24, "action_set_menu_level_faqs": 25, "utter_ask_assistance": 26, "utter_ask_name": 27, "utter_ask_option": 28, "utter_bill_muster_menu": 29, "utter_bill_muster_q1": 30, "utter_bill_muster_q2": 31, "utter_bill_muster_q3": 32, "utter_bill_muster_q4": 33, "utter_bill_muster_q5": 34, "utter_bill_muster_q6": 35, "utter_bill_muster_q7": 36, "utter_card_q1": 37, "utter_card_q10": 38, "utter_card_q11": 39, "utter_card_q12": 40, "utter_card_q13": 41, "utter_card_q14": 42, "utter_card_q15": 43, "utter_card_q16": 44, "utter_card_q17": 45, "utter_card_q18": 46, "utter_card_q19": 47, "utter_card_q2": 48, "utter_card_q20": 49, "utter_card_q3": 50, "utter_card_q4": 51, "utter_card_q5": 52, "utter_card_q6": 53, "utter_card_q7": 54, "utter_card_q8": 55, "utter_card_q9": 56, "utter_card_services_menu": 57, "utter_cheer_up": 58, "utter_credit_menu": 59, "utter_credit_q1": 60, "utter_credit_q10": 61, "utter_credit_q11": 62, "utter_credit_q12": 63, "utter_credit_q13": 64, "utter_credit_q14": 65, "utter_credit_q15": 66, "utter_credit_q16": 67, "utter_credit_q17": 68, "utter_credit_q18": 69, "utter_credit_q19": 70, "utter_credit_q2": 71, "utter_credit_q20": 72, "utter_credit_q21": 73, "utter_credit_q22": 74, "utter_credit_q23": 75, "utter_credit_q24": 76, "utter_credit_q25": 77, "utter_credit_q26": 78, "utter_credit_q27": 79, "utter_credit_q28": 80, "utter_credit_q29": 81, "utter_credit_q3": 82, "utter_credit_q4": 83, "utter_credit_q5": 84, "utter_credit_q6": 85, "utter_credit_q7": 86, "utter_credit_q8": 87, "utter_credit_q9": 88, "utter_did_that_help": 89, "utter_efts_menu": 90, "utter_efts_q1": 91, "utter_efts_q10": 92, "utter_efts_q11": 93, "utter_efts_q12": 94, "utter_efts_q13": 95, "utter_efts_q14": 96, "utter_efts_q2": 97, "utter_efts_q3": 98, "utter_efts_q4": 99, "utter_efts_q5": 100, "utter_efts_q6": 101, "utter_efts_q7": 102, "utter_efts_q8": 103, "utter_efts_q9": 104, "utter_entry_flow": 105, "utter_general_banking_menu": 106, "utter_general_q1": 107, "utter_general_q10": 108, "utter_general_q11": 109, "utter_general_q12": 110, "utter_general_q13": 111, "utter_general_q14": 112, "utter_general_q15": 113, "utter_general_q16": 114, "utter_general_q17": 115, "utter_general_q18": 116, "utter_general_q19": 117, "utter_general_q2": 118, "utter_general_q20": 119, "utter_general_q21": 120, "utter_general_q22": 121, "utter_general_q23": 122, "utter_general_q24": 123, "utter_general_q25": 124, "utter_general_q26": 125, "utter_general_q27": 126, "utter_general_q28": 127, "utter_general_q29": 128, "utter_general_q3": 129, "utter_general_q30": 130, "utter_general_q31": 131, "utter_general_q32": 132, "utter_general_q33": 133, "utter_general_q34": 134, "utter_general_q35": 135, "utter_general_q36": 136, "utter_general_q4": 137, "utter_general_q5": 138, "utter_general_q6": 139, "utter_general_q7": 140, "utter_general_q8": 141, "utter_general_q9": 142, "utter_goodbye": 143, "utter_happy": 144, "utter_iamabot": 145, "utter_internet_banking_1": 146, "utter_internet_banking_10": 147, "utter_internet_banking_11": 148, "utter_internet_banking_2": 149, "utter_internet_banking_3": 150, "utter_internet_banking_4": 151, "utter_internet_banking_5": 152, "utter_internet_banking_6": 153, "utter_internet_banking_7": 154, "utter_internet_banking_8": 155, "utter_internet_banking_9": 156, "utter_internet_banking_menu": 157, "utter_mobile_banking_menu": 158, "utter_mobile_banking_q1": 159, "utter_mobile_banking_q10": 160, "utter_mobile_banking_q11": 161, "utter_mobile_banking_q12": 162, "utter_mobile_banking_q13": 163, "utter_mobile_banking_q14": 164, "utter_mobile_banking_q15": 165, "utter_mobile_banking_q16": 166, "utter_mobile_banking_q17": 167, "utter_mobile_banking_q18": 168, "utter_mobile_banking_q19": 169, "utter_mobile_banking_q2": 170, "utter_mobile_banking_q3": 171, "utter_mobile_banking_q4": 172, "utter_mobile_banking_q5": 173, "utter_mobile_banking_q6": 174, "utter_mobile_banking_q7": 175, "utter_mobile_banking_q8": 176, "utter_mobile_banking_q9": 177, "utter_select_faq_category": 178, "utter_zanaco_xpress_1": 179, "utter_zanaco_xpress_10": 180, "utter_zanaco_xpress_11": 181, "utter_zanaco_xpress_12": 182, "utter_zanaco_xpress_13": 183, "utter_zanaco_xpress_14": 184, "utter_zanaco_xpress_15": 185, "utter_zanaco_xpress_16": 186, "utter_zanaco_xpress_17": 187, "utter_zanaco_xpress_18": 188, "utter_zanaco_xpress_19": 189, "utter_zanaco_xpress_2": 190, "utter_zanaco_xpress_3": 191, "utter_zanaco_xpress_4": 192, "utter_zanaco_xpress_5": 193, "utter_zanaco_xpress_6": 194, "utter_zanaco_xpress_7": 195, "utter_zanaco_xpress_8": 196, "utter_zanaco_xpress_9": 197, "utter_zanaco_xpress_menu": 198, "feedback_form": 199, "customer_info_form": 200, "name_form": 201}, "entities": {"menu_level": 0, "rating": 1, "request_feedback": 2}, "slots": {"menu_level_0": 0, "name_0": 1}, "active_loop": {"feedback_form": 0, "customer_info_form": 1, "name_form": 2}}, "action_texts": [], "entity_tag_specs": []}, "max_history": 5, "remove_duplicates": true}